WebCrawler_x/__init__.py
WebCrawler_x-5.2.2.dist-info/METADATA
WebCrawler_x-5.2.2.dist-info/WHEEL
WebCrawler_x-5.2.2.dist-info/top_level.txt
WebCrawler_x-5.2.2.dist-info/RECORD
