Metadata-Version: 2.1
Name: WebCrawler-x
Version: 5.2.2
Summary: UNKNOWN
Home-page: UNKNOWN
Author: jackson_tao
License: UNKNOWN
Platform: UNKNOWN
Requires-Dist: requests
Requires-Dist: retrying
Requires-Dist: beautifulsoup4
Requires-Dist: fake-useragent
Requires-Dist: gne
Requires-Dist: htmldate
Requires-Dist: loguru
Requires-Dist: lxml
Requires-Dist: lxparse
Requires-Dist: pybloom-live
Requires-Dist: DrissionPage
